README.md
setup.cfg
setup.py
tf2onnxnightly/__init__.py
tf2onnxnightly/constants.py
tf2onnxnightly/convert.py
tf2onnxnightly/flexbuffers.py
tf2onnxnightly/graph.py
tf2onnxnightly/graph_builder.py
tf2onnxnightly/graph_matcher.py
tf2onnxnightly/handler.py
tf2onnxnightly/schemas.py
tf2onnxnightly/shape_inference.py
tf2onnxnightly/tf_loader.py
tf2onnxnightly/tf_utils.py
tf2onnxnightly/tflite_utils.py
tf2onnxnightly/tfonnx.py
tf2onnxnightly/utils.py
tf2onnxnightly/verbose_logging.py
tf2onnxnightly/version.py
tf2onnxnightly.egg-info/PKG-INFO
tf2onnxnightly.egg-info/SOURCES.txt
tf2onnxnightly.egg-info/dependency_links.txt
tf2onnxnightly.egg-info/requires.txt
tf2onnxnightly.egg-info/top_level.txt
tf2onnxnightly/custom_opsets/__init__.py
tf2onnxnightly/custom_opsets/ms.py
tf2onnxnightly/custom_opsets/onnx_ml.py
tf2onnxnightly/custom_opsets/string_ops.py
tf2onnxnightly/onnx_opset/__init__.py
tf2onnxnightly/onnx_opset/common.py
tf2onnxnightly/onnx_opset/controlflow.py
tf2onnxnightly/onnx_opset/generator.py
tf2onnxnightly/onnx_opset/logical.py
tf2onnxnightly/onnx_opset/math.py
tf2onnxnightly/onnx_opset/misc.py
tf2onnxnightly/onnx_opset/nn.py
tf2onnxnightly/onnx_opset/quantize.py
tf2onnxnightly/onnx_opset/reduction.py
tf2onnxnightly/onnx_opset/rnn.py
tf2onnxnightly/onnx_opset/signal.py
tf2onnxnightly/onnx_opset/tensor.py
tf2onnxnightly/onnx_opset/traditionalml.py
tf2onnxnightly/optimizer/__init__.py
tf2onnxnightly/optimizer/back_to_back_optimizer.py
tf2onnxnightly/optimizer/const_dequantize_optimizer.py
tf2onnxnightly/optimizer/const_fold_optimizer.py
tf2onnxnightly/optimizer/identity_optimizer.py
tf2onnxnightly/optimizer/loop_optimizer.py
tf2onnxnightly/optimizer/merge_duplicated_nodes_optimizer.py
tf2onnxnightly/optimizer/optimizer_base.py
tf2onnxnightly/optimizer/transpose_optimizer.py
tf2onnxnightly/optimizer/upsample_optimizer.py
tf2onnxnightly/rewriter/__init__.py
tf2onnxnightly/rewriter/bigru_rewriter.py
tf2onnxnightly/rewriter/bilstm_rewriter.py
tf2onnxnightly/rewriter/cond_rewriter.py
tf2onnxnightly/rewriter/conv2d_with_add_rewriter.py
tf2onnxnightly/rewriter/conv2d_with_pad_rewriter.py
tf2onnxnightly/rewriter/custom_rnn_rewriter.py
