Metadata-Version: 1.1
Name: tf2onnxnightly
Version: 1.9.2
Summary: Tensorflow to ONNX converter
Home-page: https://github.com/tensorleap/tensorflow-onnx
Author: onnx@microsoft.com
Author-email: onnx@microsoft.com
License: Apache License v2.0
Download-URL: https://github.com/tensorleap/tensorflow-onnx/archive/v1.9.1-nightly-build.tar.gz
Platform: UNKNOWN
